lambda_cloud_client/__init__.py
lambda_cloud_client/api/__init__.py
lambda_cloud_client/api/default_api.py
lambda_cloud_client/api_client.py
lambda_cloud_client/api_response.py
lambda_cloud_client/configuration.py
lambda_cloud_client/exceptions.py
lambda_cloud_client/models/__init__.py
lambda_cloud_client/models/add_ssh_key200_response.py
lambda_cloud_client/models/add_ssh_key_request.py
lambda_cloud_client/models/error.py
lambda_cloud_client/models/error_code.py
lambda_cloud_client/models/error_response_body.py
lambda_cloud_client/models/file_system.py
lambda_cloud_client/models/get_instance200_response.py
lambda_cloud_client/models/instance.py
lambda_cloud_client/models/instance_type.py
lambda_cloud_client/models/instance_type_specs.py
lambda_cloud_client/models/instance_types200_response.py
lambda_cloud_client/models/instance_types200_response_data_value.py
lambda_cloud_client/models/launch_instance200_response.py
lambda_cloud_client/models/launch_instance200_response_data.py
lambda_cloud_client/models/launch_instance_request.py
lambda_cloud_client/models/list_file_systems200_response.py
lambda_cloud_client/models/list_instances200_response.py
lambda_cloud_client/models/list_ssh_keys200_response.py
lambda_cloud_client/models/region.py
lambda_cloud_client/models/restart_instance200_response.py
lambda_cloud_client/models/restart_instance200_response_data.py
lambda_cloud_client/models/restart_instance_request.py
lambda_cloud_client/models/ssh_key.py
lambda_cloud_client/models/terminate_instance200_response.py
lambda_cloud_client/models/terminate_instance200_response_data.py
lambda_cloud_client/models/terminate_instance_request.py
lambda_cloud_client/models/user.py
lambda_cloud_client/rest.py
lambda_cloud_client-1.0.0.dist-info/METADATA
lambda_cloud_client-1.0.0.dist-info/WHEEL
lambda_cloud_client-1.0.0.dist-info/RECORD
